setup.py
loweb/__init__.py
loweb.egg-info/PKG-INFO
loweb.egg-info/SOURCES.txt
loweb.egg-info/dependency_links.txt
loweb.egg-info/requires.txt
loweb.egg-info/top_level.txt