Metadata-Version: 1.0
Name: loweb
Version: 0.1.0
Summary: Tools to generate static web sites from yaml data and mustache templates
Home-page: https://github.com/gregoryv/loweb
Author: Gregory Vincic
Author-email: g@7de.se
License: GPLv3
Platform: UNKNOWN
